pip_services4_components/__init__.py
pip_services4_components/build/CompositeFactory.py
pip_services4_components/build/CreateException.py
pip_services4_components/build/Factory.py
pip_services4_components/build/IFactory.py
pip_services4_components/build/__init__.py
pip_services4_components/config/ConfigParams.py
pip_services4_components/config/IConfigurable.py
pip_services4_components/config/IReconfigurable.py
pip_services4_components/config/NameResolver.py
pip_services4_components/config/OptionsResolver.py
pip_services4_components/config/__init__.py
pip_services4_components/context/Context.py
pip_services4_components/context/ContextInfo.py
pip_services4_components/context/ContextResolver.py
pip_services4_components/context/DefaultContextFactory.py
pip_services4_components/context/IContext.py
pip_services4_components/context/__init__.py
pip_services4_components/exec/Executor.py
pip_services4_components/exec/FixedRateTimer.py
pip_services4_components/exec/IExecutable.py
pip_services4_components/exec/INotifiable.py
pip_services4_components/exec/IParameterized.py
pip_services4_components/exec/Notifier.py
pip_services4_components/exec/Parameters.py
pip_services4_components/exec/__init__.py
pip_services4_components/refer/DependencyResolver.py
pip_services4_components/refer/Descriptor.py
pip_services4_components/refer/IReferenceable.py
pip_services4_components/refer/IReferences.py
pip_services4_components/refer/IUnreferenceable.py
pip_services4_components/refer/Reference.py
pip_services4_components/refer/ReferenceException.py
pip_services4_components/refer/Referencer.py
pip_services4_components/refer/References.py
pip_services4_components/refer/__init__.py
pip_services4_components/run/Cleaner.py
pip_services4_components/run/Closer.py
pip_services4_components/run/ICleanable.py
pip_services4_components/run/IClosable.py
pip_services4_components/run/IOpenable.py
pip_services4_components/run/Opener.py
pip_services4_components/run/__init__.py
pip_services4_components-0.0.9.dist-info/LICENSE
pip_services4_components-0.0.9.dist-info/METADATA
pip_services4_components-0.0.9.dist-info/WHEEL
pip_services4_components-0.0.9.dist-info/top_level.txt
pip_services4_components-0.0.9.dist-info/zip-safe
pip_services4_components-0.0.9.dist-info/RECORD
